tortitle/__init__.py
tortitle/torsubtitle.py
tortitle/tortitle.py
tortitle-0.1.17.dist-info/licenses/LICENSE
tortitle-0.1.17.dist-info/METADATA
tortitle-0.1.17.dist-info/WHEEL
tortitle-0.1.17.dist-info/top_level.txt
tortitle-0.1.17.dist-info/RECORD
