Metadata-Version: 2.4
Name: tortitle
Version: 0.1.17
Summary: 一个用于从种⼦标题中解析电影、剧集信息的 Python 库，支持主标题和副标题的提取。
Author: ccf2012
Project-URL: Homepage, https://github.com/ccf-2012/tortitle
Project-URL: Bug Tracker, https://github.com/ccf-2012/tortitle/issues
Classifier: Programming Language :: Python :: 3
Classifier: License :: OSI Approved :: MIT License
Classifier: Operating System :: OS Independent
Requires-Python: >=3.7
License-File: LICENSE
Dynamic: license-file
